eche/__init__.py
eche/cluster.py
eche/graph_based_clustering.py
eche/py.typed
eche-0.2.1.dist-info/WHEEL
eche-0.2.1.dist-info/METADATA
eche-0.2.1.dist-info/RECORD
