Metadata-Version: 2.1
Name: eche
Version: 0.2.1
Summary: Little helper for handling entity clusters
Home-page: https://github.com/dobraczka/eche
License: MIT
Keywords: entity resolution,record linkage,clustering,connected components,transitive closure
Author: Daniel Obraczka
Author-email: obraczka@informatik.uni-leipzig.de
Requires-Python: >=3.8,<4.0
Classifier: Development Status :: 4 - Beta
Classifier: License :: OSI Approved :: MIT License
Classifier: Programming Language :: Python
Classifier: Programming Language :: Python :: 3
Classifier: Programming Language :: Python :: 3.8
Classifier: Programming Language :: Python :: 3.9
Classifier: Programming Language :: Python :: 3.10
Classifier: Programming Language :: Python :: 3.11
Classifier: Programming Language :: Python :: 3 :: Only
Classifier: Programming Language :: Python :: 3.10
Classifier: Programming Language :: Python :: 3.8
Classifier: Programming Language :: Python :: 3.9
Provides-Extra: docs
Requires-Dist: mkdocs (>=1.5.3,<2.0.0) ; extra == "docs"
Requires-Dist: mkdocs-gen-files (>=0.5.0,<0.6.0) ; extra == "docs"
Requires-Dist: mkdocs-literate-nav (>=0.6.1,<0.7.0) ; extra == "docs"
Requires-Dist: mkdocs-material (>=9.5.9,<10.0.0) ; extra == "docs"
Requires-Dist: mkdocs-section-index (>=0.3.8,<0.4.0) ; extra == "docs"
Requires-Dist: mkdocstrings[python] (>=0.24.0,<0.25.0) ; extra == "docs"
Requires-Dist: networkx
Requires-Dist: numpy
Project-URL: Bug Tracker, https://github.com/dobraczka/eche/issues
Project-URL: Documentation, https://eche.readthedocs.io
Project-URL: Repository, https://github.com/dobraczka/eche
Project-URL: Source, https://github.com/dobraczka/eche
